{"nodes":[{"id":"readme_setconca","label":"Set-ConCA","file_type":"document","source_file":"README.md","source_location":null,"source_url":null,"captured_at":null,"author":null,"contributor":null},{"id":"readme_dual_decoder","label":"Dual Decoder","file_type":"document","source_file":"README.md","source_location":null,"source_url":null,"captured_at":null,"author":null,"contributor":null},{"id":"readme_set_aggregator","label":"Set Aggregator","file_type":"document","source_file":"README.md","source_location":null,"source_url":null,"captured_at":null,"author":null,"contributor":null},{"id":"readme_cross_model_transfer","label":"Cross-Model Transfer","file_type":"document","source_file":"README.md","source_location":null,"source_url":null,"captured_at":null,"author":null,"contributor":null},{"id":"set_conca_math_sparse_conca","label":"Sparse ConCA","file_type":"paper","source_file":"set_conca_math.txt","source_location":null,"source_url":null,"captured_at":null,"author":null,"contributor":null},{"id":"set_conca_math_set_conca","label":"Set-ConCA Formalism","file_type":"paper","source_file":"set_conca_math.txt","source_location":null,"source_url":null,"captured_at":null,"author":null,"contributor":null},{"id":"set_conca_math_subset_consistency","label":"Subset Consistency Regularization","file_type":"paper","source_file":"set_conca_math.txt","source_location":null,"source_url":null,"captured_at":null,"author":null,"contributor":null},{"id":"set_conca_math_posterior_aggregation","label":"Set-Level Posterior Aggregation","file_type":"paper","source_file":"set_conca_math.txt","source_location":null,"source_url":null,"captured_at":null,"author":null,"contributor":null},{"id":"conca_math_conca_framework","label":"Concept Component Analysis (ConCA)","file_type":"paper","source_file":"conca_math.txt","source_location":null,"source_url":null,"captured_at":null,"author":null,"contributor":null},{"id":"conca_math_latent_variable_model","label":"Latent Variable Model for Text","file_type":"paper","source_file":"conca_math.txt","source_location":null,"source_url":null,"captured_at":null,"author":null,"contributor":null},{"id":"conca_math_sae","label":"Sparse Autoencoders (SAE)","file_type":"paper","source_file":"conca_math.txt","source_location":null,"source_url":null,"captured_at":null,"author":null,"contributor":null},{"id":"summery_platonic_representation_hypothesis","label":"Platonic Representation Hypothesis","file_type":"document","source_file":"summery.MD","source_location":null,"source_url":null,"captured_at":null,"author":null,"contributor":null},{"id":"summery_procrustes_bridge","label":"Linear Procrustes Bridge","file_type":"document","source_file":"summery.MD","source_location":null,"source_url":null,"captured_at":null,"author":null,"contributor":null},{"id":"summery_topk_sparsity","label":"Top-K Hard Sparsity","file_type":"document","source_file":"summery.MD","source_location":null,"source_url":null,"captured_at":null,"author":null,"contributor":null},{"id":"presentation_set_conca_presentation","label":"Set-ConCA Technical Presentation","file_type":"document","source_file":"docs/PRESENTATION.md","source_location":null,"source_url":null,"captured_at":null,"author":null,"contributor":null},{"id":"rebuttal_consistency_loss_concern","label":"Consistency Loss Rebuttal","file_type":"document","source_file":"docs/REBUTTAL_PREP.md","source_location":null,"source_url":null,"captured_at":null,"author":null,"contributor":null},{"id":"claim_traceability_partial_alignment","label":"Claim-Evidence Partial Alignment","file_type":"document","source_file":"docs/paper/claim_traceability_report.md","source_location":null,"source_url":null,"captured_at":null,"author":null,"contributor":null},{"id":"claim_traceability_artifact_requirements","label":"NeurIPS Artifact Requirements","file_type":"document","source_file":"docs/paper/claim_traceability_report.md","source_location":null,"source_url":null,"captured_at":null,"author":null,"contributor":null},{"id":"drafting_playbook_claim_calibration","label":"Claim Calibration Rules","file_type":"document","source_file":"docs/paper/drafting_playbook.md","source_location":null,"source_url":null,"captured_at":null,"author":null,"contributor":null},{"id":"figure_table_map_artifact_binding","label":"Figure-Artifact Binding Spec","file_type":"document","source_file":"docs/paper/figure_table_map.md","source_location":null,"source_url":null,"captured_at":null,"author":null,"contributor":null},{"id":"originality_positioning_set_level_analysis","label":"Set-Level Unit of Analysis","file_type":"document","source_file":"docs/paper/originality_positioning.md","source_location":null,"source_url":null,"captured_at":null,"author":null,"contributor":null},{"id":"references_audit_gde_paper","label":"GDE Reference Integration","file_type":"document","source_file":"docs/paper/references_audit_report.md","source_location":null,"source_url":null,"captured_at":null,"author":null,"contributor":null},{"id":"reproduction_report_synthetic_artifacts","label":"Synthetic Reproduction Artifacts","file_type":"document","source_file":"docs/paper/reproduction_report.md","source_location":null,"source_url":null,"captured_at":null,"author":null,"contributor":null},{"id":"submission_ready_outline_artifact_backed_claims","label":"Artifact-Backed Claims Contract","file_type":"document","source_file":"docs/paper/submission_ready_outline.md","source_location":null,"source_url":null,"captured_at":null,"author":null,"contributor":null},{"id":"test_audit_scientific_claim_gaps","label":"Scientific Claim Test Gaps","file_type":"document","source_file":"docs/paper/test_audit_report.md","source_location":null,"source_url":null,"captured_at":null,"author":null,"contributor":null},{"id":"neurips_experiment_suite_bridge_overlap","label":"NeurIPS Suite Bridge Overlap","file_type":"document","source_file":"docs/paper/artifacts/neurips_experiment_suite.md","source_location":null,"source_url":null,"captured_at":null,"author":null,"contributor":null},{"id":"graph_report_community_structure","label":"Graph Community Structure","file_type":"document","source_file":"graphify-out/GRAPH_REPORT.md","source_location":null,"source_url":null,"captured_at":null,"author":null,"contributor":null},{"id":"benchmark_deferrals_model_deferrals","label":"Multilingual Model Deferrals","file_type":"document","source_file":"results/BENCHMARK_DEFERRALS.md","source_location":null,"source_url":null,"captured_at":null,"author":null,"contributor":null}],"edges":[{"source":"readme_setconca","target":"readme_dual_decoder","relation":"references","confidence":"EXTRACTED","confidence_score":0.99,"source_file":"README.md","source_location":null,"weight":1.0},{"source":"readme_setconca","target":"readme_set_aggregator","relation":"references","confidence":"EXTRACTED","confidence_score":0.99,"source_file":"README.md","source_location":null,"weight":1.0},{"source":"readme_setconca","target":"readme_cross_model_transfer","relation":"references","confidence":"EXTRACTED","confidence_score":0.98,"source_file":"README.md","source_location":null,"weight":1.0},{"source":"set_conca_math_set_conca","target":"set_conca_math_sparse_conca","relation":"implements","confidence":"EXTRACTED","confidence_score":0.97,"source_file":"set_conca_math.txt","source_location":null,"weight":1.0},{"source":"set_conca_math_set_conca","target":"set_conca_math_subset_consistency","relation":"references","confidence":"EXTRACTED","confidence_score":0.98,"source_file":"set_conca_math.txt","source_location":null,"weight":1.0},{"source":"set_conca_math_set_conca","target":"set_conca_math_posterior_aggregation","relation":"references","confidence":"EXTRACTED","confidence_score":0.96,"source_file":"set_conca_math.txt","source_location":null,"weight":1.0},{"source":"set_conca_math_set_conca","target":"readme_setconca","relation":"semantically_similar_to","confidence":"INFERRED","confidence_score":0.89,"source_file":"set_conca_math.txt","source_location":null,"weight":1.0},{"source":"conca_math_conca_framework","target":"set_conca_math_set_conca","relation":"conceptually_related_to","confidence":"EXTRACTED","confidence_score":0.95,"source_file":"set_conca_math.txt","source_location":null,"weight":1.0},{"source":"conca_math_conca_framework","target":"conca_math_latent_variable_model","relation":"references","confidence":"EXTRACTED","confidence_score":0.97,"source_file":"conca_math.txt","source_location":null,"weight":1.0},{"source":"conca_math_conca_framework","target":"conca_math_sae","relation":"references","confidence":"EXTRACTED","confidence_score":0.94,"source_file":"conca_math.txt","source_location":null,"weight":1.0},{"source":"readme_dual_decoder","target":"set_conca_math_set_conca","relation":"conceptually_related_to","confidence":"INFERRED","confidence_score":0.84,"source_file":"README.md","source_location":null,"weight":1.0},{"source":"summery_platonic_representation_hypothesis","target":"summery_procrustes_bridge","relation":"rationale_for","confidence":"EXTRACTED","confidence_score":0.92,"source_file":"summery.MD","source_location":null,"weight":1.0},{"source":"summery_topk_sparsity","target":"rebuttal_consistency_loss_concern","relation":"rationale_for","confidence":"EXTRACTED","confidence_score":0.91,"source_file":"docs/REBUTTAL_PREP.md","source_location":null,"weight":1.0},{"source":"presentation_set_conca_presentation","target":"summery_platonic_representation_hypothesis","relation":"references","confidence":"EXTRACTED","confidence_score":0.95,"source_file":"docs/PRESENTATION.md","source_location":null,"weight":1.0},{"source":"presentation_set_conca_presentation","target":"readme_setconca","relation":"semantically_similar_to","confidence":"INFERRED","confidence_score":0.87,"source_file":"docs/PRESENTATION.md","source_location":null,"weight":1.0},{"source":"rebuttal_consistency_loss_concern","target":"summery_topk_sparsity","relation":"references","confidence":"EXTRACTED","confidence_score":0.93,"source_file":"docs/REBUTTAL_PREP.md","source_location":null,"weight":1.0},{"source":"claim_traceability_partial_alignment","target":"claim_traceability_artifact_requirements","relation":"rationale_for","confidence":"EXTRACTED","confidence_score":0.98,"source_file":"docs/paper/claim_traceability_report.md","source_location":null,"weight":1.0},{"source":"drafting_playbook_claim_calibration","target":"submission_ready_outline_artifact_backed_claims","relation":"conceptually_related_to","confidence":"EXTRACTED","confidence_score":0.96,"source_file":"docs/paper/drafting_playbook.md","source_location":null,"weight":1.0},{"source":"drafting_playbook_claim_calibration","target":"claim_traceability_partial_alignment","relation":"rationale_for","confidence":"INFERRED","confidence_score":0.82,"source_file":"docs/paper/drafting_playbook.md","source_location":null,"weight":1.0},{"source":"figure_table_map_artifact_binding","target":"claim_traceability_artifact_requirements","relation":"references","confidence":"EXTRACTED","confidence_score":0.9,"source_file":"docs/paper/figure_table_map.md","source_location":null,"weight":1.0},{"source":"originality_positioning_set_level_analysis","target":"readme_setconca","relation":"conceptually_related_to","confidence":"EXTRACTED","confidence_score":0.93,"source_file":"docs/paper/originality_positioning.md","source_location":null,"weight":1.0},{"source":"originality_positioning_set_level_analysis","target":"summery_procrustes_bridge","relation":"rationale_for","confidence":"EXTRACTED","confidence_score":0.9,"source_file":"docs/paper/originality_positioning.md","source_location":null,"weight":1.0},{"source":"references_audit_gde_paper","target":"originality_positioning_set_level_analysis","relation":"references","confidence":"EXTRACTED","confidence_score":0.88,"source_file":"docs/paper/references_audit_report.md","source_location":null,"weight":1.0},{"source":"reproduction_report_synthetic_artifacts","target":"claim_traceability_artifact_requirements","relation":"references","confidence":"EXTRACTED","confidence_score":0.9,"source_file":"docs/paper/reproduction_report.md","source_location":null,"weight":1.0},{"source":"submission_ready_outline_artifact_backed_claims","target":"claim_traceability_artifact_requirements","relation":"references","confidence":"EXTRACTED","confidence_score":0.95,"source_file":"docs/paper/submission_ready_outline.md","source_location":null,"weight":1.0},{"source":"test_audit_scientific_claim_gaps","target":"claim_traceability_partial_alignment","relation":"references","confidence":"EXTRACTED","confidence_score":0.93,"source_file":"docs/paper/test_audit_report.md","source_location":null,"weight":1.0},{"source":"neurips_experiment_suite_bridge_overlap","target":"readme_cross_model_transfer","relation":"semantically_similar_to","confidence":"EXTRACTED","confidence_score":0.86,"source_file":"docs/paper/artifacts/neurips_experiment_suite.md","source_location":null,"weight":1.0},{"source":"graph_report_community_structure","target":"readme_setconca","relation":"references","confidence":"EXTRACTED","confidence_score":0.9,"source_file":"graphify-out/GRAPH_REPORT.md","source_location":null,"weight":1.0},{"source":"benchmark_deferrals_model_deferrals","target":"readme_cross_model_transfer","relation":"conceptually_related_to","confidence":"INFERRED","confidence_score":0.78,"source_file":"results/BENCHMARK_DEFERRALS.md","source_location":null,"weight":1.0},{"source":"set_conca_math_subset_consistency","target":"rebuttal_consistency_loss_concern","relation":"conceptually_related_to","confidence":"EXTRACTED","confidence_score":0.88,"source_file":"docs/REBUTTAL_PREP.md","source_location":null,"weight":1.0},{"source":"set_conca_math_posterior_aggregation","target":"summery_platonic_representation_hypothesis","relation":"rationale_for","confidence":"INFERRED","confidence_score":0.79,"source_file":"summery.MD","source_location":null,"weight":1.0},{"source":"conca_math_sae","target":"originality_positioning_set_level_analysis","relation":"conceptually_related_to","confidence":"EXTRACTED","confidence_score":0.86,"source_file":"docs/paper/originality_positioning.md","source_location":null,"weight":1.0},{"source":"reproduction_report_synthetic_artifacts","target":"neurips_experiment_suite_bridge_overlap","relation":"conceptually_related_to","confidence":"AMBIGUOUS","confidence_score":0.52,"source_file":"docs/paper/reproduction_report.md","source_location":null,"weight":1.0}],"hyperedges":[{"id":"setconca_claim_governance_bundle","label":"Set-ConCA Claim Governance Bundle","nodes":["claim_traceability_partial_alignment","drafting_playbook_claim_calibration","figure_table_map_artifact_binding","submission_ready_outline_artifact_backed_claims","test_audit_scientific_claim_gaps"],"relation":"form","confidence":"EXTRACTED","confidence_score":0.93,"source_file":"docs/paper/drafting_playbook.md"},{"id":"setconca_theory_to_system_bundle","label":"ConCA to Set-ConCA Theory-System Bundle","nodes":["conca_math_conca_framework","set_conca_math_set_conca","readme_setconca","summery_procrustes_bridge"],"relation":"participate_in","confidence":"INFERRED","confidence_score":0.81,"source_file":"set_conca_math.txt"}],"input_tokens":0,"output_tokens":0}
