{"nodes": [{"id": "fig08_training_convergence_plateau", "label": "Training Convergence Plateau Near Epoch 50", "file_type": "image", "source_file": "results/figures/fig08_convergence.png", "source_location": null, "source_url": null, "captured_at": null, "author": null, "contributor": null}], "edges": [{"source": "fig08_training_convergence_plateau", "target": "report_setconca_framework", "relation": "rationale_for", "confidence": "EXTRACTED", "confidence_score": 0.9, "source_file": "results/figures/fig08_convergence.png", "source_location": null, "weight": 0.87}], "hyperedges": []}