{"nodes": [{"id": "setconca_model_setconca_py", "label": "setconca.py", "file_type": "code", "source_file": "setconca\\model\\setconca.py", "source_location": "L1"}, {"id": "setconca_setconca", "label": "SetConCA", "file_type": "code", "source_file": "setconca\\model\\setconca.py", "source_location": "L9"}, {"id": "setconca_setconca_init", "label": ".__init__()", "file_type": "code", "source_file": "setconca\\model\\setconca.py", "source_location": "L10"}, {"id": "setconca_setconca_encode_and_aggregate", "label": ".encode_and_aggregate()", "file_type": "code", "source_file": "setconca\\model\\setconca.py", "source_location": "L18"}, {"id": "setconca_setconca_forward", "label": ".forward()", "file_type": "code", "source_file": "setconca\\model\\setconca.py", "source_location": "L31"}, {"id": "setconca_compute_loss", "label": "compute_loss()", "file_type": "code", "source_file": "setconca\\model\\setconca.py", "source_location": "L37"}], "edges": [{"source": "setconca_model_setconca_py", "target": "torch", "relation": "imports", "confidence": "EXTRACTED", "source_file": "setconca\\model\\setconca.py", "source_location": "L1", "weight": 1.0}, {"source": "setconca_model_setconca_py", "target": "torch_nn", "relation": "imports", "confidence": "EXTRACTED", "source_file": "setconca\\model\\setconca.py", "source_location": "L2", "weight": 1.0}, {"source": "setconca_model_setconca_py", "target": "setconca_model_encoder_py", "relation": "imports_from", "confidence": "EXTRACTED", "source_file": "setconca\\model\\setconca.py", "source_location": "L3", "weight": 1.0}, {"source": "setconca_model_setconca_py", "target": "setconca_model_aggregator_py", "relation": "imports_from", "confidence": "EXTRACTED", "source_file": "setconca\\model\\setconca.py", "source_location": "L4", "weight": 1.0}, {"source": "setconca_model_setconca_py", "target": "setconca_model_decoder_py", "relation": "imports_from", "confidence": "EXTRACTED", "source_file": "setconca\\model\\setconca.py", "source_location": "L5", "weight": 1.0}, {"source": "setconca_model_setconca_py", "target": "setconca_losses_sparsity_py", "relation": "imports_from", "confidence": "EXTRACTED", "source_file": "setconca\\model\\setconca.py", "source_location": "L6", "weight": 1.0}, {"source": "setconca_model_setconca_py", "target": "setconca_losses_consistency_py", "relation": "imports_from", "confidence": "EXTRACTED", "source_file": "setconca\\model\\setconca.py", "source_location": "L7", "weight": 1.0}, {"source": "setconca_model_setconca_py", "target": "setconca_setconca", "relation": "contains", "confidence": "EXTRACTED", "source_file": "setconca\\model\\setconca.py", "source_location": "L9", "weight": 1.0}, {"source": "setconca_setconca", "target": "setconca_setconca_init", "relation": "method", "confidence": "EXTRACTED", "source_file": "setconca\\model\\setconca.py", "source_location": "L10", "weight": 1.0}, {"source": "setconca_setconca", "target": "setconca_setconca_encode_and_aggregate", "relation": "method", "confidence": "EXTRACTED", "source_file": "setconca\\model\\setconca.py", "source_location": "L18", "weight": 1.0}, {"source": "setconca_setconca", "target": "setconca_setconca_forward", "relation": "method", "confidence": "EXTRACTED", "source_file": "setconca\\model\\setconca.py", "source_location": "L31", "weight": 1.0}, {"source": "setconca_model_setconca_py", "target": "setconca_compute_loss", "relation": "contains", "confidence": "EXTRACTED", "source_file": "setconca\\model\\setconca.py", "source_location": "L37", "weight": 1.0}, {"source": "setconca_setconca_forward", "target": "setconca_setconca_encode_and_aggregate", "relation": "calls", "confidence": "EXTRACTED", "source_file": "setconca\\model\\setconca.py", "source_location": "L32", "weight": 1.0}]}